eskapadespark/__init__.py
eskapadespark/data_conversion.py
eskapadespark/decorators.py
eskapadespark/exceptions.py
eskapadespark/functions.py
eskapadespark/helpers.py
eskapadespark/resources.py
eskapadespark/spark_manager.py
eskapadespark/version.py
eskapadespark/config/spark/spark.cfg
eskapadespark/data/correlated_data.sv.gz
eskapadespark/data/dummy.csv
eskapadespark/data/dummy1.csv
eskapadespark/data/dummy2.csv
eskapadespark/data/dummy_time_series.csv
eskapadespark/data/mock_accounts.csv.gz
eskapadespark/jdbc/__init__.py
eskapadespark/jdbc/jdbcconnection.py
eskapadespark/jdbc/links/__init__.py
eskapadespark/jdbc/links/jdbc_reader.py
eskapadespark/links/__init__.py
eskapadespark/links/daily_summary.py
eskapadespark/links/find_days_until_event.py
eskapadespark/links/hive_reader.py
eskapadespark/links/hive_writer.py
eskapadespark/links/rdd_group_mapper.py
eskapadespark/links/spark_configurator.py
eskapadespark/links/spark_data_to_csv.py
eskapadespark/links/spark_df_converter.py
eskapadespark/links/spark_df_creator.py
eskapadespark/links/spark_df_reader.py
eskapadespark/links/spark_df_writer.py
eskapadespark/links/spark_execute_query.py
eskapadespark/links/spark_histogrammar_filler.py
eskapadespark/links/spark_streaming_controller.py
eskapadespark/links/spark_streaming_wordcount.py
eskapadespark/links/spark_streaming_writer.py
eskapadespark/links/spark_with_column.py
eskapadespark/links/sparkgeneralfuncprocessor.py
eskapadespark/links/sparkhister.py
eskapadespark/tutorials/__init__.py
eskapadespark/tutorials/esk601_spark_configuration.py
eskapadespark/tutorials/esk602_read_csv_to_spark_df.py
eskapadespark/tutorials/esk603_write_spark_data_to_csv.py
eskapadespark/tutorials/esk604_spark_execute_query.py
eskapadespark/tutorials/esk605_create_spark_df.py
eskapadespark/tutorials/esk606_convert_spark_df.py
eskapadespark/tutorials/esk607_spark_with_column.py
eskapadespark/tutorials/esk608_spark_histogrammar.py
eskapadespark/tutorials/esk609_map_df_groups.py
Eskapade_Spark-1.0.0.dist-info/LICENSE
Eskapade_Spark-1.0.0.dist-info/METADATA
Eskapade_Spark-1.0.0.dist-info/NOTICE
Eskapade_Spark-1.0.0.dist-info/WHEEL
Eskapade_Spark-1.0.0.dist-info/top_level.txt
Eskapade_Spark-1.0.0.dist-info/RECORD
