Metadata-Version: 2.1
Name: Eskapade-Spark
Version: 1.0.0
Summary: Spark for Eskapade
Home-page: http://eskapade.kave.io
Author: KPMG N.V. The Netherlands
Author-email: kave@kpmg.com
License: UNKNOWN
Platform: UNKNOWN
Requires-Python: >=3.5
Requires-Dist: Eskapade-Core (>=1.0.0)
Requires-Dist: Eskapade (>=1.0.0)
Requires-Dist: pyspark (>=2.1.2)
Requires-Dist: jaydebeapi (>=1.1.1)
Requires-Dist: pytest (>=3.5.0)
Requires-Dist: pytest-pylint (>=0.9.0)
